deterministic_keygen-0.0.7.dist-info/METADATA
deterministic_keygen-0.0.7.dist-info/WHEEL
deterministic_keygen-0.0.7.dist-info/license_files/LICENSE
deterministic_keygen/__init__.py
deterministic_keygen/__init__.pyi
deterministic_keygen/py.typed
deterministic_keygen/deterministic_keygen.cpython-311-s390x-linux-gnu.so
deterministic_keygen-0.0.7.dist-info/RECORD
