Metadata-Version: 2.3
Name: deterministic-keygen
Version: 0.0.7
Classifier: Development Status :: 3 - Alpha
Classifier: Intended Audience :: Developers
Classifier: License :: DFSG approved
Classifier: License :: OSI Approved
Classifier: License :: OSI Approved :: MIT License
Classifier: Natural Language :: English
Classifier: Programming Language :: Python
Classifier: Programming Language :: Python :: 3
Classifier: Programming Language :: Python :: 3.8
Classifier: Programming Language :: Python :: 3.9
Classifier: Programming Language :: Python :: 3.10
Classifier: Programming Language :: Python :: 3.11
Classifier: Programming Language :: Python :: 3.12
Classifier: Programming Language :: Python :: 3 :: Only
Classifier: Programming Language :: Python :: Implementation :: CPython
Classifier: Programming Language :: Python :: Implementation :: PyPy
Classifier: Programming Language :: Rust
Classifier: Topic :: Security :: Cryptography
License-File: LICENSE
Summary: Deterministic key-generator
Keywords: deterministic,key-generator,bip39,rsa
Author-email: "Christopher R. Wood" <chris@cyberethics.ca>
License: MIT
Requires-Python: >=3.8
Project-URL: Issues, https://github.com/crwood/deterministic-keygen/issues
Project-URL: Source, https://github.com/crwood/deterministic-keygen
